{"title": "The Case of the Franks", "season": "4 ", "episode": "13", "description": "Seth and Summer come upon a fortune teller whose prediction makes the two question whether they are truly meant for each other. Ryan gets back in touch with his father (with a little help ...\n                    See full summary\u00a0\u00bb", "rating": "7.7/10", "total_vote": "302", "airdate": "Episode aired 1 February 2007", "runtime": "44min", "list_of_the_cast": "Peter Gallagher  as  Sandy Cohen\nKelly Rowan  as  Kirsten Cohen\nBen McKenzie  as  Ryan Atwood\nAdam Brody  as  Seth Cohen\nMelinda Clarke  as  Julie Cooper\nRachel Bilson  as  Summer Roberts\nAutumn Reeser  as  Taylor Townsend\nWilla Holland  as  Kaitlin Cooper\nKevin Sorbo  as  Frank Atwood\nGary Grubbs  as  Gordon Bullit\nMax Greenfield  as  Young Sandy Cohen\nEllen Hollman  as  Young Kirsten Nichol\nGraham Miller  as  Young Jimmy Cooper\nCathy Lind Hayes  as  The Teacher\nViji Nathan  as  The Psychic"}