{"title": "The Way We Were", "season": "2 ", "episode": "2", "description": "The boys are back. Every status is quo. Except: Summer won't kiss and make up. Ryan catches Marissa in a clinch, the DA busts Caleb, Hailey bails and the re-modelers are like a wrecking crew. Home sweet chaos.", "rating": "7.9/10", "total_vote": "351", "airdate": "Episode aired 11 November 2004", "runtime": "43min", "list_of_the_cast": "Peter Gallagher  as  Sandy Cohen\nKelly Rowan  as  Kirsten Cohen\nBen McKenzie  as  Ryan Atwood\nMischa Barton  as  Marissa Cooper\nAdam Brody  as  Seth Cohen\nMelinda Clarke  as  Julie Cooper-Nichol\nRachel Bilson  as  Summer Roberts\nAlan Dale  as  Caleb Nichol\nTate Donovan  as  Jimmy Cooper\nAmanda Righetti  as  Hailey Nichol\nMichael Cassidy  as  Zach Stevens\nNicholas Gonzalez  as  D.J.\nBruno Amato  as  Archie\nMichelle Hurd  as  Ms. Fisher\nGreg Callahan  as  Plainclothes Cop"}